README.rst
setup.cfg
setup.py
modularconfig/__init__.py
modularconfig/config_manager.py
modularconfig/errors.py
modularconfig.egg-info/PKG-INFO
modularconfig.egg-info/SOURCES.txt
modularconfig.egg-info/dependency_links.txt
modularconfig.egg-info/requires.txt
modularconfig.egg-info/top_level.txt
modularconfig.egg-info/zip-safe
modularconfig/loaders/__init__.py
modularconfig/loaders/base64.py
modularconfig/loaders/bool.py
modularconfig/loaders/complex.py
modularconfig/loaders/datatype.py
modularconfig/loaders/float.py
modularconfig/loaders/ini.py
modularconfig/loaders/int.py
modularconfig/loaders/json_.py
modularconfig/loaders/none.py
modularconfig/loaders/number.py
modularconfig/loaders/python.py
modularconfig/loaders/text.py
modularconfig/loaders/yaml_.py