Metadata-Version: 2.1
Name: modularconfig
Version: 0.2.4a0
Summary: Modular config loader
Home-page: https://github.com/zannabianca1997/modularconfig
Author: Giuseppe Zanichelli
Author-email: zannabianca199712@gmail.com
License: BSD
Download-URL: https://github.com/zannabianca1997/modularconfig/archive/v_0.2.4-alpha.tar.gz
Keywords: configs,modular
Platform: UNKNOWN
Classifier: Development Status :: 3 - Alpha
Classifier: Intended Audience :: Developers
Classifier: License :: OSI Approved :: BSD License
Classifier: Programming Language :: Python :: 3
Requires-Python: >=3.6
Provides-Extra: yaml
